django_cas_ng/__init__.py
django_cas_ng/apps.py
django_cas_ng/backends.py
django_cas_ng/decorators.py
django_cas_ng/middleware.py
django_cas_ng/models.py
django_cas_ng/py.typed
django_cas_ng/signals.py
django_cas_ng/utils.py
django_cas_ng/views.py
django_cas_ng/locale/ca/LC_MESSAGES/django.mo
django_cas_ng/locale/ca/LC_MESSAGES/django.po
django_cas_ng/locale/de/LC_MESSAGES/django.mo
django_cas_ng/locale/de/LC_MESSAGES/django.po
django_cas_ng/locale/es/LC_MESSAGES/django.mo
django_cas_ng/locale/es/LC_MESSAGES/django.po
django_cas_ng/locale/fr/LC_MESSAGES/django.mo
django_cas_ng/locale/fr/LC_MESSAGES/django.po
django_cas_ng/locale/ru/LC_MESSAGES/django.mo
django_cas_ng/locale/ru/LC_MESSAGES/django.po
django_cas_ng/locale/ua/LC_MESSAGES/django.mo
django_cas_ng/locale/ua/LC_MESSAGES/django.po
django_cas_ng/management/__init__.py
django_cas_ng/management/commands/__init__.py
django_cas_ng/management/commands/django_cas_ng_clean_sessions.py
django_cas_ng/migrations/0001_initial.py
django_cas_ng/migrations/0002_auto_20201023_1400.py
django_cas_ng/migrations/0003_auto_20210813_1226.py
django_cas_ng/migrations/__init__.py
django_cas_ng-5.0.1.dist-info/LICENSE.txt
django_cas_ng-5.0.1.dist-info/METADATA
django_cas_ng-5.0.1.dist-info/WHEEL
django_cas_ng-5.0.1.dist-info/top_level.txt
django_cas_ng-5.0.1.dist-info/RECORD
